{
    "generatedAt":  "2026-03-07T21:39:01.9095162Z",
    "requiredFileTypes":  [
                              "team",
                              "players",
                              "appearence",
                              "formation",
                              "squad"
                          ],
    "teams":  [
                  {
                      "folder":  "manchester-united",
                      "displayName":  "Manchester United",
                      "files":  {
                                    "appearence":  "MANCHESTER UNITED_appearence.csv",
                                    "formation":  "MANCHESTER UNITED_formation.csv",
                                    "players":  "MANCHESTER UNITED_players.csv",
                                    "squad":  "MANCHESTER UNITED_squad.csv",
                                    "team":  "MANCHESTER UNITED_team.csv"
                                },
                      "missingRequired":  [

                                          ]
                  }
              ]
}
